tronpy/__init__.py
tronpy/abi.py
tronpy/async_contract.py
tronpy/async_tron.py
tronpy/contract.py
tronpy/defaults.py
tronpy/exceptions.py
tronpy/tron.py
tronpy/keys/__init__.py
tronpy/providers/__init__.py
tronpy/providers/async_http.py
tronpy/providers/http.py
nobi_tronpy-1.0.0.dist-info/LICENSE
nobi_tronpy-1.0.0.dist-info/METADATA
nobi_tronpy-1.0.0.dist-info/WHEEL
nobi_tronpy-1.0.0.dist-info/top_level.txt
nobi_tronpy-1.0.0.dist-info/RECORD
