Metadata-Version: 2.1
Name: nobi-tronpy
Version: 1.0.0
Summary: TRON Python client library
Home-page: https://github.com/nobbennob/nobi-tronpy
Author: andelf
Author-email: andelf@gmail.com
Requires-Python: >=3.6,<4.0
License-File: LICENSE
Requires-Dist: base58 (<3.0.0,>=2.0.0)
Requires-Dist: eth-abi (<3.0.0,>=2.1.1)
Requires-Dist: pycryptodome (<4.0.0,>=3.9.7)
Requires-Dist: requests (<3.0.0,>=2.23.0)
